FreeAI/__init__.py
FreeAI/generator.py
FreeAI/logger.py
FreeAI/memory.py
FreeAI-1.1.0.dist-info/METADATA
FreeAI-1.1.0.dist-info/WHEEL
FreeAI-1.1.0.dist-info/top_level.txt
FreeAI-1.1.0.dist-info/RECORD
