Metadata-Version: 2.1
Name: FreeAI
Version: 1.1.0
Summary: FreeAI is a powerful Python package that utilizes the advanced capabilities of GPT (Generative Pre-trained Transformer) models for text generation. It allows users to generate creative and context-aware text based on a given prompt. Whether you need to generate code snippets, creative writing pieces, or technical documentation, FreeAI has got you covered.
Author: Ashiq Hussain
Author-email: Ashiq Hussain <imseldrith@gmail.com>
Project-URL: Homepage, https://github.com/mir-ashiq/FreeAI
Project-URL: Bug Tracker, https://github.com/mir-ashiq/FreeAI/issues
Classifier: Programming Language :: Python :: 3
Classifier: License :: OSI Approved :: MIT License
Classifier: Operating System :: OS Independent
Requires-Python: >=3.7
Requires-Dist: requests
Requires-Dist: python-dateutil
